a2svm/__init__.py
a2svm/a2svm.py
a2svm/ressources.py
a2svm-0.1.5.dist-info/METADATA
a2svm-0.1.5.dist-info/WHEEL
a2svm-0.1.5.dist-info/entry_points.txt
a2svm-0.1.5.dist-info/top_level.txt
a2svm-0.1.5.dist-info/RECORD
