Metadata-Version: 2.1
Name: a2svm
Version: 0.1.5
Summary: Simple CLI tool to create and delete easily virtual hosts in Apache.
Home-page: https://github.com/cypx/a2svm
Author: Cyprien Devillez
Author-email: cyp@bidouille.info
License: GPL
Platform: UNKNOWN
Classifier: Programming Language :: Python
Classifier: License :: OSI Approved
Classifier: Natural Language :: English
Classifier: Programming Language :: Python :: 2.6
Classifier: Programming Language :: Python :: 2.7
Classifier: Programming Language :: Python :: 3.4
Classifier: Programming Language :: Python :: 3.5
Classifier: Programming Language :: Python :: 3.6
Classifier: Topic :: System
Classifier: Topic :: Utilities
Classifier: Development Status :: 4 - Beta
Requires-Dist: appdirs
Requires-Dist: argparse
Requires-Dist: configparser ; python_version < "3"
Requires-Dist: future ; python_version < "3"
